{
  "project_info": {
    "project_number": "695176998694",
    "project_id": "biletuygulamasi",
    "storage_bucket": "biletuygulamasi.appspot.com"
  },
  "client": [
    {
      "client_info": {
        "mobilesdk_app_id": "1:695176998694:android:a60ebd76bc685dde8f1be7",
        "android_client_info": {
          "package_name": "com.example.biletuygulama"
        }
      },
      "oauth_client": [
        {
          "client_id": "695176998694-ssmic9g2p9qrkr9ea3e35ucireko4d9r.apps.googleusercontent.com",
          "client_type": 3
        }
      ],
      "api_key": [
        {
          "current_key": "AIzaSyCsdKTfVU2FlExMzrI-aCMMD5OHflnUB3Q"
        }
      ],
      "services": {
        "appinvite_service": {
          "other_platform_oauth_client": [
            {
              "client_id": "695176998694-ssmic9g2p9qrkr9ea3e35ucireko4d9r.apps.googleusercontent.com",
              "client_type": 3
            },
            {
              "client_id": "695176998694-73hu2jmpn68ojqjcnufk5gsn5tsfvm4k.apps.googleusercontent.com",
              "client_type": 2,
              "ios_info": {
                "bundle_id": "com.example.busTicketUnap"
              }
            }
          ]
        }
      }
    },
    {
      "client_info": {
        "mobilesdk_app_id": "1:695176998694:android:19e5d2991ee1eb5a8f1be7",
        "android_client_info": {
          "package_name": "com.example.bus_ticket"
        }
      },
      "oauth_client": [
        {
          "client_id": "695176998694-ssmic9g2p9qrkr9ea3e35ucireko4d9r.apps.googleusercontent.com",
          "client_type": 3
        }
      ],
      "api_key": [
        {
          "current_key": "AIzaSyCsdKTfVU2FlExMzrI-aCMMD5OHflnUB3Q"
        }
      ],
      "services": {
        "appinvite_service": {
          "other_platform_oauth_client": [
            {
              "client_id": "695176998694-ssmic9g2p9qrkr9ea3e35ucireko4d9r.apps.googleusercontent.com",
              "client_type": 3
            },
            {
              "client_id": "695176998694-73hu2jmpn68ojqjcnufk5gsn5tsfvm4k.apps.googleusercontent.com",
              "client_type": 2,
              "ios_info": {
                "bundle_id": "com.example.busTicketUnap"
              }
            }
          ]
        }
      }
    },
    {
      "client_info": {
        "mobilesdk_app_id": "1:695176998694:android:8a4b6bcae6c15eba8f1be7",
        "android_client_info": {
          "package_name": "com.example.bus_ticket_unap"
        }
      },
      "oauth_client": [
        {
          "client_id": "695176998694-ssmic9g2p9qrkr9ea3e35ucireko4d9r.apps.googleusercontent.com",
          "client_type": 3
        }
      ],
      "api_key": [
        {
          "current_key": "AIzaSyCsdKTfVU2FlExMzrI-aCMMD5OHflnUB3Q"
        }
      ],
      "services": {
        "appinvite_service": {
          "other_platform_oauth_client": [
            {
              "client_id": "695176998694-ssmic9g2p9qrkr9ea3e35ucireko4d9r.apps.googleusercontent.com",
              "client_type": 3
            },
            {
              "client_id": "695176998694-73hu2jmpn68ojqjcnufk5gsn5tsfvm4k.apps.googleusercontent.com",
              "client_type": 2,
              "ios_info": {
                "bundle_id": "com.example.busTicketUnap"
              }
            }
          ]
        }
      }
    },
    {
      "client_info": {
        "mobilesdk_app_id": "1:695176998694:android:0618b4d55e404e538f1be7",
        "android_client_info": {
          "package_name": "com.example.snemabilet"
        }
      },
      "oauth_client": [
        {
          "client_id": "695176998694-ssmic9g2p9qrkr9ea3e35ucireko4d9r.apps.googleusercontent.com",
          "client_type": 3
        }
      ],
      "api_key": [
        {
          "current_key": "AIzaSyCsdKTfVU2FlExMzrI-aCMMD5OHflnUB3Q"
        }
      ],
      "services": {
        "appinvite_service": {
          "other_platform_oauth_client": [
            {
              "client_id": "695176998694-ssmic9g2p9qrkr9ea3e35ucireko4d9r.apps.googleusercontent.com",
              "client_type": 3
            },
            {
              "client_id": "695176998694-73hu2jmpn68ojqjcnufk5gsn5tsfvm4k.apps.googleusercontent.com",
              "client_type": 2,
              "ios_info": {
                "bundle_id": "com.example.busTicketUnap"
              }
            }
          ]
        }
      }
    }
  ],
  "configuration_version": "1"
}